_agorartc.cpython-39-darwin.so
agorartc.py
AgoraAIDenoiseExtension.framework/AgoraAIDenoiseExtension
AgoraAIDenoiseExtension.framework/Versions/A/AgoraAIDenoiseExtension
AgoraAIDenoiseExtension.framework/Versions/A/Resources/Info.plist
AgoraCore.framework/AgoraCore
AgoraCore.framework/Versions/A/AgoraCore
AgoraCore.framework/Versions/A/Resources/Info.plist
AgoraDav1dExtension.framework/AgoraDav1dExtension
AgoraDav1dExtension.framework/Versions/A/AgoraDav1dExtension
AgoraDav1dExtension.framework/Versions/A/Resources/Info.plist
AgoraJNDExtension.framework/AgoraJNDExtension
AgoraJNDExtension.framework/Versions/A/AgoraJNDExtension
AgoraJNDExtension.framework/Versions/A/Resources/Info.plist
AgoraRtcKit.framework/AgoraRtcKit
AgoraRtcKit.framework/Versions/A/AgoraRtcKit
AgoraRtcKit.framework/Versions/A/Headers/AgoraAudioFrame.h
AgoraRtcKit.framework/Versions/A/Headers/AgoraBase.h
AgoraRtcKit.framework/Versions/A/Headers/AgoraConstants.h
AgoraRtcKit.framework/Versions/A/Headers/AgoraEnumerates.h
AgoraRtcKit.framework/Versions/A/Headers/AgoraLogWriter.h
AgoraRtcKit.framework/Versions/A/Headers/AgoraMediaIO.h
AgoraRtcKit.framework/Versions/A/Headers/AgoraMediaMetadata.h
AgoraRtcKit.framework/Versions/A/Headers/AgoraObjects.h
AgoraRtcKit.framework/Versions/A/Headers/AgoraRtcChannel.h
AgoraRtcKit.framework/Versions/A/Headers/AgoraRtcEngineKit.h
AgoraRtcKit.framework/Versions/A/Headers/IAgoraLog.h
AgoraRtcKit.framework/Versions/A/Headers/IAgoraMediaEngine.h
AgoraRtcKit.framework/Versions/A/Headers/IAgoraRtcChannel.h
AgoraRtcKit.framework/Versions/A/Headers/IAgoraRtcEngine.h
AgoraRtcKit.framework/Versions/A/Headers/IAgoraService.h
AgoraRtcKit.framework/Versions/A/Modules/module.modulemap
AgoraRtcKit.framework/Versions/A/Resources/Info.plist
AgoraSoundTouch.framework/AgoraSoundTouch
AgoraSoundTouch.framework/Versions/A/AgoraSoundTouch
AgoraSoundTouch.framework/Versions/A/Resources/Info.plist
Agorafdkaac.framework/Agorafdkaac
Agorafdkaac.framework/Versions/A/Agorafdkaac
agora_python_sdk-3.4.2.1.dist-info/LICENSE
agora_python_sdk-3.4.2.1.dist-info/METADATA
agora_python_sdk-3.4.2.1.dist-info/WHEEL
agora_python_sdk-3.4.2.1.dist-info/top_level.txt
agora_python_sdk-3.4.2.1.dist-info/RECORD
