Metadata-Version: 2.1
Name: agora-python-sdk
Version: 3.4.2.1
Summary: Agora RTC Python SDK
Home-page: https://github.com/AgoraIO-Community/Agora-Python-SDK
Author: Agora.io
License: UNKNOWN
Platform: UNKNOWN
Classifier: Programming Language :: Python :: 3
Classifier: Development Status :: 4 - Beta
Classifier: License :: OSI Approved :: MIT License
Classifier: Operating System :: MacOS
Classifier: Operating System :: Microsoft :: Windows
Classifier: Topic :: Scientific/Engineering
Classifier: Topic :: Software Development :: Libraries
Classifier: Topic :: Multimedia :: Video
Classifier: Topic :: Multimedia :: Video :: Capture
Classifier: Programming Language :: C++
Requires-Python: >=3.6
